[{"Ano":2020,"Mes_Num":1,"Mes_Nome":"Janeiro","Receita_Bruta":32851.85,"Custos_Variaveis":703180.55,"Despesas_Operacionais":214491.65,"Indice_Novo":1},{"Ano":2020,"Mes_Num":2,"Mes_Nome":"Fevereiro","Receita_Bruta":22103.81,"Custos_Variaveis":719439.63,"Despesas_Operacionais":231773.44,"Indice_Novo":2},{"Ano":2020,"Mes_Num":3,"Mes_Nome":"Marco","Receita_Bruta":42830.63,"Custos_Variaveis":783665.13,"Despesas_Operacionais":228261.26,"Indice_Novo":3},{"Ano":2020,"Mes_Num":4,"Mes_Nome":"Abril","Receita_Bruta":36448.15,"Custos_Variaveis":283565.15,"Despesas_Operacionais":220363.49,"Indice_Novo":4},{"Ano":2020,"Mes_Num":5,"Mes_Nome":"Maio","Receita_Bruta":34962.02,"Custos_Variaveis":601290.8,"Despesas_Operacionais":209100.95,"Indice_Novo":5},{"Ano":2020,"Mes_Num":6,"Mes_Nome":"Junho","Receita_Bruta":7576.54,"Custos_Variaveis":544203.52,"Despesas_Operacionais":173138.0,"Indice_Novo":6},{"Ano":2020,"Mes_Num":7,"Mes_Nome":"Julho","Receita_Bruta":54665.73,"Custos_Variaveis":1282376.6200000001,"Despesas_Operacionais":185811.03,"Indice_Novo":7},{"Ano":2020,"Mes_Num":8,"Mes_Nome":"Agosto","Receita_Bruta":46720.45,"Custos_Variaveis":804794.26,"Despesas_Operacionais":189981.26,"Indice_Novo":8},{"Ano":2020,"Mes_Num":9,"Mes_Nome":"Setembro","Receita_Bruta":115940.3,"Custos_Variaveis":449674.65,"Despesas_Operacionais":225693.98,"Indice_Novo":9},{"Ano":2020,"Mes_Num":10,"Mes_Nome":"Outubro","Receita_Bruta":30284.88,"Custos_Variaveis":826950.02,"Despesas_Operacionais":228684.84,"Indice_Novo":10},{"Ano":2020,"Mes_Num":11,"Mes_Nome":"Novembro","Receita_Bruta":53409.83,"Custos_Variaveis":548052.0600000001,"Despesas_Operacionais":192810.65,"Indice_Novo":11},{"Ano":2020,"Mes_Num":12,"Mes_Nome":"Dezembro","Receita_Bruta":133448.85,"Custos_Variaveis":1350314.8700000001,"Despesas_Operacionais":163570.59,"Indice_Novo":12},{"Ano":2021,"Mes_Num":1,"Mes_Nome":"Janeiro","Receita_Bruta":53565.44,"Custos_Variaveis":990942.96,"Despesas_Operacionais":206565.86,"Indice_Novo":13},{"Ano":2021,"Mes_Num":2,"Mes_Nome":"Fevereiro","Receita_Bruta":59708.81,"Custos_Variaveis":1374981.55,"Despesas_Operacionais":233561.59,"Indice_Novo":14},{"Ano":2021,"Mes_Num":3,"Mes_Nome":"Marco","Receita_Bruta":66118.45,"Custos_Variaveis":1318448.1699999999,"Despesas_Operacionais":317433.87,"Indice_Novo":15},{"Ano":2021,"Mes_Num":4,"Mes_Nome":"Abril","Receita_Bruta":34024.56,"Custos_Variaveis":1325936.3,"Despesas_Operacionais":262597.71,"Indice_Novo":16},{"Ano":2021,"Mes_Num":5,"Mes_Nome":"Maio","Receita_Bruta":82540.14,"Custos_Variaveis":1153734.22,"Despesas_Operacionais":254871.02,"Indice_Novo":17},{"Ano":2021,"Mes_Num":6,"Mes_Nome":"Junho","Receita_Bruta":77777.69,"Custos_Variaveis":916974.72,"Despesas_Operacionais":218784.42,"Indice_Novo":18},{"Ano":2021,"Mes_Num":7,"Mes_Nome":"Julho","Receita_Bruta":154176.34,"Custos_Variaveis":1106788.96,"Despesas_Operacionais":219941.62,"Indice_Novo":19},{"Ano":2021,"Mes_Num":8,"Mes_Nome":"Agosto","Receita_Bruta":64171.73,"Custos_Variaveis":1195403.3,"Despesas_Operacionais":289537.34,"Indice_Novo":20},{"Ano":2021,"Mes_Num":9,"Mes_Nome":"Setembro","Receita_Bruta":98699.24,"Custos_Variaveis":1225615.0900000001,"Despesas_Operacionais":194774.95,"Indice_Novo":21},{"Ano":2021,"Mes_Num":10,"Mes_Nome":"Outubro","Receita_Bruta":58461.69,"Custos_Variaveis":1385888.03,"Despesas_Operacionais":370601.21,"Indice_Novo":22},{"Ano":2021,"Mes_Num":11,"Mes_Nome":"Novembro","Receita_Bruta":62319.15,"Custos_Variaveis":1551687.6299999999,"Despesas_Operacionais":313017.95,"Indice_Novo":23},{"Ano":2021,"Mes_Num":12,"Mes_Nome":"Dezembro","Receita_Bruta":251401.87,"Custos_Variaveis":1543834.3600000001,"Despesas_Operacionais":257081.8,"Indice_Novo":24},{"Ano":2022,"Mes_Num":1,"Mes_Nome":"Janeiro","Receita_Bruta":54126.05,"Custos_Variaveis":494575.02,"Despesas_Operacionais":237219.42,"Indice_Novo":25},{"Ano":2022,"Mes_Num":2,"Mes_Nome":"Fevereiro","Receita_Bruta":51987.3,"Custos_Variaveis":1097280.6899999999,"Despesas_Operacionais":296947.96,"Indice_Novo":26},{"Ano":2022,"Mes_Num":3,"Mes_Nome":"Marco","Receita_Bruta":83191.36,"Custos_Variaveis":1188350.78,"Despesas_Operacionais":288840.36,"Indice_Novo":27},{"Ano":2022,"Mes_Num":4,"Mes_Nome":"Abril","Receita_Bruta":448229.12,"Custos_Variaveis":1101584.97,"Despesas_Operacionais":308468.61,"Indice_Novo":28},{"Ano":2022,"Mes_Num":5,"Mes_Nome":"Maio","Receita_Bruta":75151.28,"Custos_Variaveis":779339.6,"Despesas_Operacionais":384108.48,"Indice_Novo":29},{"Ano":2022,"Mes_Num":6,"Mes_Nome":"Junho","Receita_Bruta":43823.84,"Custos_Variaveis":889629.21,"Despesas_Operacionais":272633.09,"Indice_Novo":30},{"Ano":2022,"Mes_Num":7,"Mes_Nome":"Julho","Receita_Bruta":39899.82,"Custos_Variaveis":2770853.5499999998,"Despesas_Operacionais":302007.82,"Indice_Novo":31},{"Ano":2022,"Mes_Num":8,"Mes_Nome":"Agosto","Receita_Bruta":87848.73,"Custos_Variaveis":2699656.02,"Despesas_Operacionais":392164.76,"Indice_Novo":32},{"Ano":2022,"Mes_Num":9,"Mes_Nome":"Setembro","Receita_Bruta":69519.01,"Custos_Variaveis":2384088.3500000001,"Despesas_Operacionais":424499.35,"Indice_Novo":33},{"Ano":2022,"Mes_Num":10,"Mes_Nome":"Outubro","Receita_Bruta":209124.71,"Custos_Variaveis":2065780.01,"Despesas_Operacionais":404467.33,"Indice_Novo":34},{"Ano":2022,"Mes_Num":11,"Mes_Nome":"Novembro","Receita_Bruta":59190.72,"Custos_Variaveis":2836865.8900000001,"Despesas_Operacionais":447056.12,"Indice_Novo":35},{"Ano":2022,"Mes_Num":12,"Mes_Nome":"Dezembro","Receita_Bruta":1155891.3899999999,"Custos_Variaveis":1202832.28,"Despesas_Operacionais":222795.1,"Indice_Novo":36},{"Ano":2023,"Mes_Num":1,"Mes_Nome":"Janeiro","Receita_Bruta":36460.85,"Custos_Variaveis":438360.46,"Despesas_Operacionais":307637.1,"Indice_Novo":37},{"Ano":2023,"Mes_Num":2,"Mes_Nome":"Fevereiro","Receita_Bruta":111383.6,"Custos_Variaveis":1266817.1100000001,"Despesas_Operacionais":280621.35,"Indice_Novo":38},{"Ano":2023,"Mes_Num":3,"Mes_Nome":"Marco","Receita_Bruta":67565.54,"Custos_Variaveis":3336350.3700000001,"Despesas_Operacionais":416402.06,"Indice_Novo":39},{"Ano":2023,"Mes_Num":4,"Mes_Nome":"Abril","Receita_Bruta":164437.24,"Custos_Variaveis":1132258.6799999999,"Despesas_Operacionais":519870.0,"Indice_Novo":40},{"Ano":2023,"Mes_Num":5,"Mes_Nome":"Maio","Receita_Bruta":68978.81,"Custos_Variaveis":1096948.1000000001,"Despesas_Operacionais":192432.85,"Indice_Novo":41},{"Ano":2023,"Mes_Num":6,"Mes_Nome":"Junho","Receita_Bruta":60039.65,"Custos_Variaveis":761099.52,"Despesas_Operacionais":169670.65,"Indice_Novo":42},{"Ano":2023,"Mes_Num":7,"Mes_Nome":"Julho","Receita_Bruta":113068.2,"Custos_Variaveis":983745.3100000001,"Despesas_Operacionais":157888.51,"Indice_Novo":43},{"Ano":2023,"Mes_Num":8,"Mes_Nome":"Agosto","Receita_Bruta":81649.93,"Custos_Variaveis":1976562.74,"Despesas_Operacionais":153079.47,"Indice_Novo":44},{"Ano":2023,"Mes_Num":9,"Mes_Nome":"Setembro","Receita_Bruta":106250.07,"Custos_Variaveis":3289237.7400000002,"Despesas_Operacionais":249772.7,"Indice_Novo":45},{"Ano":2023,"Mes_Num":10,"Mes_Nome":"Outubro","Receita_Bruta":105112.86,"Custos_Variaveis":2475164.5299999998,"Despesas_Operacionais":180734.33,"Indice_Novo":46},{"Ano":2023,"Mes_Num":11,"Mes_Nome":"Novembro","Receita_Bruta":50089.05,"Custos_Variaveis":1275597.76,"Despesas_Operacionais":222877.14,"Indice_Novo":47},{"Ano":2023,"Mes_Num":12,"Mes_Nome":"Dezembro","Receita_Bruta":5497071.9199999999,"Custos_Variaveis":1007534.4300000001,"Despesas_Operacionais":105381.46,"Indice_Novo":48},{"Ano":2024,"Mes_Num":1,"Mes_Nome":"Janeiro","Receita_Bruta":46011.91,"Custos_Variaveis":821107.33,"Despesas_Operacionais":149909.97,"Indice_Novo":49},{"Ano":2024,"Mes_Num":2,"Mes_Nome":"Fevereiro","Receita_Bruta":69227.16,"Custos_Variaveis":2990803.6499999999,"Despesas_Operacionais":171699.81,"Indice_Novo":50},{"Ano":2024,"Mes_Num":3,"Mes_Nome":"Marco","Receita_Bruta":74388.82,"Custos_Variaveis":2760399.0699999998,"Despesas_Operacionais":232303.29,"Indice_Novo":51},{"Ano":2024,"Mes_Num":4,"Mes_Nome":"Abril","Receita_Bruta":43882.14,"Custos_Variaveis":1748687.1599999999,"Despesas_Operacionais":203794.69,"Indice_Novo":52},{"Ano":2024,"Mes_Num":5,"Mes_Nome":"Maio","Receita_Bruta":80479.66,"Custos_Variaveis":2006048.1000000001,"Despesas_Operacionais":207229.99,"Indice_Novo":53},{"Ano":2024,"Mes_Num":6,"Mes_Nome":"Junho","Receita_Bruta":38635.46,"Custos_Variaveis":1386426.03,"Despesas_Operacionais":114984.06,"Indice_Novo":54},{"Ano":2024,"Mes_Num":7,"Mes_Nome":"Julho","Receita_Bruta":62484.21,"Custos_Variaveis":1454811.75,"Despesas_Operacionais":421584.16,"Indice_Novo":55},{"Ano":2024,"Mes_Num":8,"Mes_Nome":"Agosto","Receita_Bruta":5781.54,"Custos_Variaveis":1878811.52,"Despesas_Operacionais":257410.08,"Indice_Novo":56},{"Ano":2024,"Mes_Num":9,"Mes_Nome":"Setembro","Receita_Bruta":156865.59,"Custos_Variaveis":1750813.4399999999,"Despesas_Operacionais":183616.97,"Indice_Novo":57},{"Ano":2024,"Mes_Num":10,"Mes_Nome":"Outubro","Receita_Bruta":87978.34,"Custos_Variaveis":1620378.0900000001,"Despesas_Operacionais":175866.85,"Indice_Novo":58},{"Ano":2024,"Mes_Num":11,"Mes_Nome":"Novembro","Receita_Bruta":38340.35,"Custos_Variaveis":1808005.0700000001,"Despesas_Operacionais":333093.19,"Indice_Novo":59},{"Ano":2024,"Mes_Num":12,"Mes_Nome":"Dezembro","Receita_Bruta":116128.68,"Custos_Variaveis":634663.62,"Despesas_Operacionais":109497.85,"Indice_Novo":60},{"Ano":2025,"Mes_Num":1,"Mes_Nome":"Janeiro","Receita_Bruta":36104.29,"Custos_Variaveis":2226293.3399999999,"Despesas_Operacionais":224523.05,"Indice_Novo":61},{"Ano":2025,"Mes_Num":2,"Mes_Nome":"Fevereiro","Receita_Bruta":45695.4,"Custos_Variaveis":1661647.3799999999,"Despesas_Operacionais":226817.8,"Indice_Novo":62},{"Ano":2025,"Mes_Num":3,"Mes_Nome":"Marco","Receita_Bruta":68630.26,"Custos_Variaveis":1281409.3799999999,"Despesas_Operacionais":267051.34,"Indice_Novo":63},{"Ano":2025,"Mes_Num":4,"Mes_Nome":"Abril","Receita_Bruta":38965.15,"Custos_Variaveis":1723625.9199999999,"Despesas_Operacionais":176247.42,"Indice_Novo":64},{"Ano":2025,"Mes_Num":5,"Mes_Nome":"Maio","Receita_Bruta":53770.27,"Custos_Variaveis":1752343.29,"Despesas_Operacionais":209475.39,"Indice_Novo":65},{"Ano":2025,"Mes_Num":6,"Mes_Nome":"Junho","Receita_Bruta":419254.49,"Custos_Variaveis":743697.84,"Despesas_Operacionais":208869.57,"Indice_Novo":66},{"Ano":2025,"Mes_Num":7,"Mes_Nome":"Julho","Receita_Bruta":49505.45,"Custos_Variaveis":479989.68,"Despesas_Operacionais":188383.18,"Indice_Novo":67},{"Ano":2025,"Mes_Num":8,"Mes_Nome":"Agosto","Receita_Bruta":85841.38,"Custos_Variaveis":1445697.3200000001,"Despesas_Operacionais":197212.26,"Indice_Novo":68},{"Ano":2025,"Mes_Num":9,"Mes_Nome":"Setembro","Receita_Bruta":79525.3,"Custos_Variaveis":1029824.17,"Despesas_Operacionais":240319.8,"Indice_Novo":69},{"Ano":2025,"Mes_Num":10,"Mes_Nome":"Outubro","Receita_Bruta":104347.17,"Custos_Variaveis":1431912.1899999999,"Despesas_Operacionais":162092.19,"Indice_Novo":70},{"Ano":2025,"Mes_Num":11,"Mes_Nome":"Novembro","Receita_Bruta":53571.13,"Custos_Variaveis":563935.4,"Despesas_Operacionais":269498.43,"Indice_Novo":71},{"Ano":2025,"Mes_Num":12,"Mes_Nome":"Dezembro","Receita_Bruta":988318.72,"Custos_Variaveis":433628.58,"Despesas_Operacionais":283557.15,"Indice_Novo":72},{"Ano":2026,"Mes_Num":1,"Mes_Nome":"Janeiro","Receita_Bruta":94662.36,"Custos_Variaveis":191920.5,"Despesas_Operacionais":205157.0,"Indice_Novo":73},{"Ano":2026,"Mes_Num":2,"Mes_Nome":"Fevereiro","Receita_Bruta":93907.93,"Custos_Variaveis":1246154.49,"Despesas_Operacionais":167932.55,"Indice_Novo":74},{"Ano":2026,"Mes_Num":3,"Mes_Nome":"Marco","Receita_Bruta":108820.14,"Custos_Variaveis":1721185.95,"Despesas_Operacionais":196716.07,"Indice_Novo":75},{"Ano":2026,"Mes_Num":4,"Mes_Nome":"Abril","Receita_Bruta":62614.42,"Custos_Variaveis":2069149.79,"Despesas_Operacionais":194850.75,"Indice_Novo":76},{"Ano":2026,"Mes_Num":5,"Mes_Nome":"Maio","Receita_Bruta":46132.12,"Custos_Variaveis":761910.67,"Despesas_Operacionais":178886.2,"Indice_Novo":77},{"Ano":2026,"Mes_Num":6,"Mes_Nome":"Junho","Receita_Bruta":84850.92,"Custos_Variaveis":528189.8100000001,"Despesas_Operacionais":142407.59,"Indice_Novo":78},{"Ano":2026,"Mes_Num":7,"Mes_Nome":"Julho","Receita_Bruta":0.0,"Custos_Variaveis":1710.18,"Despesas_Operacionais":25215.51,"Indice_Novo":79},{"Ano":2026,"Mes_Num":8,"Mes_Nome":"Agosto","Receita_Bruta":0.0,"Custos_Variaveis":0.0,"Despesas_Operacionais":0.0,"Indice_Novo":80},{"Ano":2026,"Mes_Num":9,"Mes_Nome":"Setembro","Receita_Bruta":0.0,"Custos_Variaveis":0.0,"Despesas_Operacionais":0.0,"Indice_Novo":81},{"Ano":2026,"Mes_Num":10,"Mes_Nome":"Outubro","Receita_Bruta":0.0,"Custos_Variaveis":0.0,"Despesas_Operacionais":0.0,"Indice_Novo":82},{"Ano":2026,"Mes_Num":11,"Mes_Nome":"Novembro","Receita_Bruta":0.0,"Custos_Variaveis":0.0,"Despesas_Operacionais":0.0,"Indice_Novo":83},{"Ano":2026,"Mes_Num":12,"Mes_Nome":"Dezembro","Receita_Bruta":0.0,"Custos_Variaveis":0.0,"Despesas_Operacionais":0.0,"Indice_Novo":84}]